{
	"Task1":[
		{
			"address":"",
			"Node[x]":"",
			"a":"",
			"b":"",
			"c":""
		},
		{
			"address":"",
			"Node[x]":"",
			"a":"",
			"b":"",
			"c":""
		},
		{
			"address":"",
			"Node[x]":"",
			"a":"",
			"b":"",
			"c":""
		},
		{
			"address":"",
			"Node[x]":"",
			"a":"",
			"b":"",
			"c":""
		},
		{
			"address":"",
			"Node[x]":"",
			"a":"",
			"b":"",
			"c":""
		}
	],
	"Task2":{
		"nodes":"",
		"nodes.a":"",
		"nodes[3].a":"",
		"nodes[3].c":"",
		"nodes[3].c->a":"",
		"*nodes.a":"",
		"(*nodes).a":"",
		"nodes->a":"",
		"nodes[3].b->b":"",
		"&nodes[3].a":"",
		"&nodes[3].c":"",
		"&nodes[3].c->a":"",
		"&nodes->a":"",
		"np":"",
		"np->a":"",
		"np->c->c->a":"",
		"npp":"",
		"npp->a":"",
		"*npp":"",
		"*npp->a":"",
		"(*npp)->a":"",
		"&np":"",
		"&np->a":"",
		"&np->c->c->a":""
	}
	
}
